fastmcp_agents/library/agent/filesystem_operations/__init__.py
fastmcp_agents/library/agent/filesystem_operations/agent.py
fastmcp_agents_library_agent_filesystem_operations-0.5.7.dist-info/WHEEL
fastmcp_agents_library_agent_filesystem_operations-0.5.7.dist-info/entry_points.txt
fastmcp_agents_library_agent_filesystem_operations-0.5.7.dist-info/METADATA
fastmcp_agents_library_agent_filesystem_operations-0.5.7.dist-info/RECORD
